kakaotrans/__init__.py
kakaotrans/constants.py
kakaotrans/translator.py
kakaotrans-0.1.2.dist-info/LICENSE
kakaotrans-0.1.2.dist-info/METADATA
kakaotrans-0.1.2.dist-info/WHEEL
kakaotrans-0.1.2.dist-info/top_level.txt
kakaotrans-0.1.2.dist-info/RECORD
