Metadata-Version: 2.1
Name: kakaotrans
Version: 0.1.2
Summary: [Unofficial] Kakaotrans: Kakao translate API for python
Home-page: https://github.com/monologg/kakaotrans
Author: Jangwon Park
Author-email: adieujw@gmail.com
License: MIT
Platform: UNKNOWN
Classifier: Programming Language :: Python :: 3
Classifier: License :: OSI Approved :: MIT License
Classifier: Operating System :: OS Independent
Requires-Python: >=3
Requires-Dist: requests
